pysmilesutils/__init__.py
pysmilesutils/analyze.py
pysmilesutils/augment.py
pysmilesutils/datautils.py
pysmilesutils/tokenize.py
syntheseus_PySMILESutils-1.1.0.dist-info/LICENSE
syntheseus_PySMILESutils-1.1.0.dist-info/METADATA
syntheseus_PySMILESutils-1.1.0.dist-info/WHEEL
syntheseus_PySMILESutils-1.1.0.dist-info/top_level.txt
syntheseus_PySMILESutils-1.1.0.dist-info/RECORD
